KorDigits/__init__.py
KorDigits/generate_num.py
KorDigits/run_cls_LSTM.py
KorDigits/model/LSTM_CLS_Model.py
KorDigits/results/save_model/lstm_kt_model.pt
KorDigits/utils/cls_data_parsing.py
KorDigits/utils/convert_num_unit.py
KorDigits/utils/data_parsing.py
KorDigits/utils/kor_pronun_unit.TXT
KorDigits/utils/num_unit.py
KorDigits/utils/word_dict.json
KorDigits/utils/KoCharELECTRA/test_kocharelectra.py
KorDigits/utils/KoCharELECTRA/tokenization_kocharelectra.py
KorDigits-1.2.11.dist-info/METADATA
KorDigits-1.2.11.dist-info/WHEEL
KorDigits-1.2.11.dist-info/top_level.txt
KorDigits-1.2.11.dist-info/RECORD
