Metadata-Version: 2.1
Name: KorDigits
Version: 1.2.11
Summary: number to Korean word
Home-page: https://github.com/jukyung-j/Korean_numeral
Author: jukyung-j
Author-email: wjdwnrud123@naver.com
License: jukyung-j
Requires-Dist: jamo (==0.4.1)
Requires-Dist: konlpy (==0.6.0)
Requires-Dist: transformers (==4.26.1)
Requires-Dist: eunjeon (==0.4.0)
